myMath_yao/__init__.py
myMath_yao/addition.py
myMath_yao/multiplication.py
myMath_yao-0.2.dist-info/LICENSE
myMath_yao-0.2.dist-info/METADATA
myMath_yao-0.2.dist-info/WHEEL
myMath_yao-0.2.dist-info/top_level.txt
myMath_yao-0.2.dist-info/RECORD
