Metadata-Version: 2.1
Name: myMath-yao
Version: 0.2
Summary: A simple math package
Home-page: https://github.com/yourusername/mymath
Author: Your Name
Author-email: your.email@example.com
License: UNKNOWN
Platform: UNKNOWN
Classifier: Programming Language :: Python :: 3
Classifier: License :: OSI Approved :: MIT License
Classifier: Operating System :: OS Independent
Requires-Python: >=3.6
License-File: LICENSE
